tokyo_lineage/__init__.py
tokyo_lineage/adapter/__init__.py
tokyo_lineage/adapter/client_facade.py
tokyo_lineage/adapter/openlineage.py
tokyo_lineage/extractor/__init__.py
tokyo_lineage/extractor/airflow_extractor.py
tokyo_lineage/extractor/base.py
tokyo_lineage/facets/__init__.py
tokyo_lineage/facets/annotation.py
tokyo_lineage/integrations/__init__.py
tokyo_lineage/integrations/airflow/__init__.py
tokyo_lineage/integrations/airflow/extract_lineage_operator.py
tokyo_lineage/integrations/airflow/hooks/__init__.py
tokyo_lineage/integrations/airflow/hooks/mongo_hook.py
tokyo_lineage/metadata_extractor/__init__.py
tokyo_lineage/metadata_extractor/base.py
tokyo_lineage/metadata_extractor/airflow/__init__.py
tokyo_lineage/metadata_extractor/airflow/airflow_default.py
tokyo_lineage/metadata_extractor/airflow/bigquery_extractor.py
tokyo_lineage/metadata_extractor/airflow/file_to_gcs_extractor.py
tokyo_lineage/metadata_extractor/airflow/gcs_to_bigquery_extractor.py
tokyo_lineage/metadata_extractor/airflow/mongo_to_avro_extractor.py
tokyo_lineage/metadata_extractor/airflow/mysql_to_avro_extractor.py
tokyo_lineage/metadata_extractor/airflow/postgres_extractor.py
tokyo_lineage/metadata_extractor/airflow/postgres_to_avro_extractor.py
tokyo_lineage/models/__init__.py
tokyo_lineage/models/airflow_dag.py
tokyo_lineage/models/airflow_task.py
tokyo_lineage/models/base.py
tokyo_lineage/utils/__init__.py
tokyo_lineage/utils/airflow.py
tokyo_lineage/utils/avro.py
tokyo_lineage/utils/dataset_naming_helper.py
tokyo_lineage/utils/hash.py
tokyo_lineage/utils/logging_mixin.py
tokyo_lineage/utils/parser/__init__.py
tokyo_lineage/utils/parser/dictionary.py
tokyo_lineage/utils/parser/lexer.py
tokyo_lineage/utils/parser/parser.py
tokyo_lineage/utils/parser/tokens.py
tokyo_lineage/utils/parser/utils.py
tokyo_lineage-0.6a15.dist-info/LICENSE
tokyo_lineage-0.6a15.dist-info/METADATA
tokyo_lineage-0.6a15.dist-info/WHEEL
tokyo_lineage-0.6a15.dist-info/top_level.txt
tokyo_lineage-0.6a15.dist-info/RECORD
